je_open_cv/__init__.py
je_open_cv/template_detection.py
je_open_cv/modules/__init__.py
je_open_cv/modules/contours.py
je_open_cv/modules/draw.py
je_open_cv/modules/edge.py
je_open_cv/modules/face_detection.py
je_open_cv/modules/feature.py
je_open_cv/modules/feature_detection.py
je_open_cv/modules/fourier.py
je_open_cv/modules/fps.py
je_open_cv/modules/gradients.py
je_open_cv/modules/histograms.py
je_open_cv/modules/hough_line.py
je_open_cv/modules/image_operations.py
je_open_cv/modules/io.py
je_open_cv/modules/morphological.py
je_open_cv/modules/object_tracking.py
je_open_cv/modules/pyramids.py
je_open_cv/modules/smoothing.py
je_open_cv/modules/template_detection.py
je_open_cv/modules/thresholding.py
je_open_cv/modules/ui.py
je_open_cv/modules/video.py
je_open_cv-0.0.20.dist-info/LICENSE
je_open_cv-0.0.20.dist-info/METADATA
je_open_cv-0.0.20.dist-info/WHEEL
je_open_cv-0.0.20.dist-info/top_level.txt
je_open_cv-0.0.20.dist-info/RECORD
