Metadata-Version: 2.1
Name: je-open-cv
Version: 0.0.20
Summary: JEChen's OpenCV wrapper
Home-page: https://github.com/JE-Chen/je_opencv_wrapper
Author: JE-Chen
Author-email: zenmailman@gmail.com
License: UNKNOWN
Platform: UNKNOWN
Classifier: Programming Language :: Python :: 3.5
Classifier: Development Status :: 2 - Pre-Alpha
Classifier: Environment :: Win32 (MS Windows)
Classifier: Environment :: MacOS X
Classifier: Environment :: X11 Applications
Classifier: License :: OSI Approved :: MIT License
Classifier: Operating System :: OS Independent
Requires-Dist: opencv-python
Requires-Dist: numpy
